tokenROI-0.6.7.dist-info/LICENSE.txt
tokenROI-0.6.7.dist-info/METADATA
tokenROI-0.6.7.dist-info/RECORD
tokenROI-0.6.7.dist-info/WHEEL
tokenROI-0.6.7.dist-info/entry_points.txt
tokenROI-0.6.7.dist-info/top_level.txt
token_roi/__init__.py
token_roi/__main__.py
token_roi/arg_parser.py
token_roi/cloud_storage.py
token_roi/config.py
token_roi/token_mailer.py
token_roi/tokens.py
