Metadata-Version: 2.1
Name: tokenROI
Version: 0.6.7
Summary: Quick ROI calculator for your token balances base on idex.market prices
Home-page: https://github.com/mrowacz/tokenROI
Author: Lukasz Czerwinski
Author-email: mrowacz@gmail.com
License: MIT
Keywords: tokens cryptocurrencies idex roi
Platform: UNKNOWN
Classifier: Development Status :: 1 - Planning
Classifier: License :: OSI Approved :: MIT License
Classifier: Programming Language :: Python
Classifier: Programming Language :: Python :: 3
Classifier: Programming Language :: Python :: 3.5
Requires-Dist: python-editor
Requires-Dist: dropbox
Requires-Dist: requests (>=2.16.2)
